cllm_data_curation/__init__.py
cllm_data_curation/parallel_dl/__init__.py
cllm_data_curation/parallel_dl/multiprocessing_utils.py
cllm_data_curation/parallel_dl/other_utils.py
cllm_data_curation/parallel_dl/parallel_dl.py
cllm_data_curation/parallel_dl/preprocessing_utils.py
cllm_data_curation/parallel_dl/processing_utils.py
cllm_data_curation/thestack_curation/__init__.py
cllm_data_curation/thestack_curation/curation_configs.py
cllm_data_curation/thestack_curation/curation_utils.py
cllm_data_curation/thestack_curation/download.py
cllm_data_curation/thestack_curation/download_utils.py
cllm_data_curation/thestack_curation/general_utils.py
cllm_data_curation-0.1.2.dist-info/METADATA
cllm_data_curation-0.1.2.dist-info/WHEEL
cllm_data_curation-0.1.2.dist-info/top_level.txt
cllm_data_curation-0.1.2.dist-info/RECORD
