Metadata-Version: 2.1
Name: cllm-data-curation
Version: 0.1.2
Summary: A package to visualize tokenization of text using HTML
Home-page: https://github.com/ds08tf/cllm-data-curation
Author: Darien Schettler
Author-email: ds08tf@gmail.com
Classifier: Development Status :: 3 - Alpha
Classifier: Intended Audience :: Developers
Classifier: License :: OSI Approved :: MIT License
Classifier: Programming Language :: Python :: 3
Classifier: Programming Language :: Python :: 3.7
Classifier: Programming Language :: Python :: 3.8
Classifier: Programming Language :: Python :: 3.9
Requires-Python: >=3.7
Requires-Dist: huggingface-hub
Requires-Dist: transformers
Requires-Dist: datasets
Requires-Dist: requests
Requires-Dist: pandas
Requires-Dist: numpy
Requires-Dist: tqdm
Requires-Dist: chardet
Requires-Dist: python-magic
